{"1":["Fecha Vta","Fecha visita","Tipo Doc","Nro Doc","Apellido","Nombre","Calle","Numero","Piso","Depto","Localidad","Cod.Postal","Tel\u00e9fono","Tel\u00e9fono","mail","Horario","IMP. RENDIR","Producto","Reproceso S\/N","Observaci\u00f3n","Doc. Pedir"],"2":[43263,43266,96,"26716883","ALBACHIARA","DARIO EZEQUIEL","JUAN HIPOLITO VIEYTES","3082","00","0","SANTA FE","3000","03424606443","0342155229453",null,"10:00 A 12:00",null,null,null,"ENTRE CALLES URQUIZA Y 4 DE ENERO",null],"3":[43263,43266,96,"16818109","LOPEZ","CLAUDIA A","ITUZAINGO","2067","0","0","SANTA FE","3000","03424541690","03424541690",null,"14 A 16 HS ",null,null,null,"ENTRE CALLES: LAS HERAS Y  ALVEAR \nIR LO MAS TEMPRANO POSIBLE EN ESA FRANJA HORARIA ",null],"4":[43263,43266,96,"32730132","MURINGA","BRENDA PENELOPE","ENTRE RIOS","4103","00","0","SANTA FE","3000","03424582255","",null,"11:00HS A 13:00HS",null,null,null,"ENTRE RIOS Y JUAN DIAZ SOLIS EN LA ESQUINA\n\n",null],"5":[43263,43266,96,"29560757","RINCON","LORENA GABINA","AVELLANEDA","5020","0","0","SANTA FE","3000","0342155662183","0342155662183",null,"16:00 A 18:00",null,null,null,"ENTRE CALLES: CALCENA Y AGUSTIN DELGADO\nSI PUEDE SER A LAS 17 HS MEJOR.",null],"6":[43263,43266,96,"22861021","SUMANO","DANIEL EDUARDO","RICADO ALDAO","2308","-","-","SANTA FE","3000","03424698903","0342154340898",null,"DE 9 A 11 HS ",null,null,null,"",null],"7":[43263,43266,96,"17857718","TERRIZZANO","FLORENCIA MARIA","COUNTRY EL PASO LOTE 57","KM 153","-","-","SANTO TOME","3000","03424820075","155015026",null,"13:30 A 14:30 HS",null,null,null,"DIR:AUTOPISTA SANTAFE - ROSARIO KM 153.EN FRENTE DEL HOTEL DEL CLUB COLON.LLAMAR ANTES DE IR (ING X OESTE)342155015026(HABLAR POR WPP X CUALQUIER DUDA DE COMO LLEGAR)",null],"8":[43263,43266,96,"30706644","ZAISER","FABRICIO MANUEL","SAN MARTIN","1317","-0","-0","SANTA FE","3000","0342156335898","0342156335898",null,"09 HS  A 11 HS",null,null,null,"ES SU DOMICILIO LABORAL EN EL SENADO, IR A LA OFICINA 1 QUE ES LA DEL SENADOR GRAMAJO\nOFICINA 1 (SENADOR GRAMAJO)",null],"9":[43264,43266,96,"25157403","COLLI","NATALIA MARIEL","LAVAISSE","2363","0","0","SANTA FE","3000","03424693211","0342154480213",null,"9 A 11",null,null,null,"",null],"10":[43264,43266,96,"27480832","PAGANO","NADIA CAROLINA","9 DE JULIO","7156","0","01","SANTA FE","3000","03424696459","0342155147875",null,"11.00 A 13",null,null,null,"Q EL GESTOR LE AVISE UNA HORA ANTES DE LLEGAR ASI SE ENCUENTRA SEGURO , ,E PIDIO Q LA LLAME AL CELULAR 0342\/155147875",null],"11":[43264,43266,96,"12437152","RAMIREZ","SILVIA CRISTINA","PJE. GALISTEO","2173","00","0","SANTA FE","3000","03424559152","0342154499935",null,"16:00 A 18:00",null,null,null,"ENTRE CALLES SALTA Y LISANDRO DE LA  TORRE ",null],"12":[43264,43266,96,"05961165","SOTO","MIRIAN GRACIELA","B EL PAZO MZ 17 VIV 44","00","-","-","SANTA FE","3000","03424511436","0342154301185",null,"10:00HS A 12:00HS ",null,null,null,"ENTRE  CALLES 17 Y 18 (PASA ORTIZ DE MONTOSH) \nBARRIO EL POZO ",null],"13":[43265,43266,96,"11903591","ABALOS","SUSANA MARGARITA","PJE BRAILE","2711","00","0","SANTA FE","3000","03424550043","",null,"9 A 11 ",null,null,null,"",null],"14":[43265,43266,96,"21048499","ARREDONDO","JUAN ALBERTO","PRES SANTIAGO DERQUI","3450","00","0","SANTA FE","3000","03424560313","0342154382445",null,"13 A 15 HS ",null,null,null,"",null],"15":[43265,43266,96,"12719180","AVELLANEDA","JUANA ANGELICA","LUCIANO MOLINAS","1834","0","0","SANTA FE","3000","03424559588","",null,"16 A 18 HS ",null,null,null,"",null],"16":[43265,43266,96,"14992714","CHIA","ANA MERCEDES","PADRE QUIROGA","2483","-0","-0","SANTA FE","3000","03424560851","0342155085078",null,"14:00 A  16:00",null,null,null,"GOLPEAR FUERTE PORTON VERDE!!!\nENTRE CALLES 1\u00b0 JUNTA Y TUCUMAN(CASI LLEGANDO A TUCUMAN)",null],"17":[43265,43266,96,"17876525","ENRIQUEZ","ALEJANDRA BEATRIZ","LAVALLE","6560","0","0","SANTA FE","3000","03424692002","0342156150063",null,"16:00A 18:00 HS .",null,null,null,"ENTRE CALLES:ARNADIA Y J PELOPE.",null],"18":[43265,43266,96,"16400450","FERNANDEZ","CARMEN","CORDOBA","1755","00","00","SANTA FE","3000","0342154873246","0342154873246",null,"10:00 A 12:00HS",null,null,null,"CORDOBA Y NECOCHEA CEL 342-15-4873246 ",null],"19":[43265,43266,96,"14402491","GARCILAZO","ANA MATILDE","LAS FLORES II M 20 ESC.13","1171","03","0","SANTA FE","3000","03424840774","",null,"9 A 11 ",null,null,null,"",null],"20":[43265,43266,96,"11316052","GONZALEZ","CARLOS DAVID","GDOR. LUCIANO MOLINAS","1834","00","0","SANTA FE","3000","03424559588","",null,"09 A 12",null,null,null,"",null],"21":[43265,43266,96,"16948301","GONZALEZ","STELLA MARIS","J P LOPEZ","3475","0","0","SANTA FE","3000","03424898770","0342154185936",null,"09 11 ",null,null,null,"",null],"22":[43265,43266,96,"29142075","MENDOZA","ROBERTO AGUSTIN","GABOTO","4652","00","0","SANTA FE","3000","03424562014","03425397974",null,"9:00 A 11:00 HS .",null,null,null,"ENTRE CALLES: ARTIGAS Y PERU",null],"23":[43265,43266,96,"11524754","POLERAT","BELKIS BEATRIZ","GORRITI","1660","00","0","SANTA FE","3000","03424696823","0342155034137",null,"16 HS A 18HS ",null,null,null,"ENTRE CALLES SARMIENTO Y ALBERDI",null],"24":[43265,43266,96,"20258650","RISTORTO","DANIELA","MENDOZA","4151","-","-","SANTA FE","3000","03424585433","0342154212157",null,"9:00HS A 11:00HS",null,null,null,"HOSPITAL DE NI\u00d1O. GIMNASIO SERVICO DE REHABILTACION\nENTRE: MENDOZA Y SALTA, SOLIS Y LA MADRID\n\n",null],"25":[43265,43266,96,"23738382","SALVA","MARIA JOSE","SAN GERONIMO","3337","-","-","SANTA FE","3000","03424557604","0342156111337",null,"9:00HS A 11 HS",null,null,null,"DOMICILIO LABORAL: SANATORIO SAN GERONIMO\nELLA EST\u00c1 DE  9 A 13 EN EL SANATORIO",null]}